.bumpversion.cfg
.pre-commit-config.yaml
.readthedocs.yml
AUTHORS.md
CONTRIBUTING.md
HISTORY.md
LICENSE
MANIFEST.in
Makefile
README.md
pyproject.toml
setup.cfg
setup.py
docs/Makefile
docs/authors.rst
docs/conf.py
docs/contributing.rst
docs/coordinate_systems.rst
docs/examples.rst
docs/history.rst
docs/index.rst
docs/installation.rst
docs/make.bat
docs/modules.rst
docs/readme.rst
docs/requirements.txt
docs/scene.rst
docs/usage.rst
docs/yt_idv.cameras.rst
docs/yt_idv.misc.rst
docs/yt_idv.rendering_contexts.rst
docs/yt_idv.scene_annotations.rst
docs/yt_idv.scene_components.rst
docs/yt_idv.scene_data.rst
docs/yt_idv.scene_graph.rst
docs/resources/sph-vr-example.png
examples/amr_offscreen.py
examples/amr_osmesa.py
examples/amr_volume_rendering.py
examples/amr_volume_rendering_with_curves.py
examples/block_collection_normalization.py
examples/grid_positions.py
examples/hires_galaxy.py
examples/idv_widget.ipynb
examples/manual_amr_scene_graph.py
examples/mesh_render.py
examples/multiview_rendering.py
examples/octree_volume_rendering.py
examples/particle_rendering.py
examples/sph_rendering.py
examples/spherical_amr_rendering_with_refinement.py
examples/spherical_unigrid_rendering.py
yt_idv/__init__.py
yt_idv/_cmyt_utilities.py
yt_idv/cli.py
yt_idv/constants.py
yt_idv/gui_support.py
yt_idv/opengl_support.py
yt_idv/scene_graph.py
yt_idv/shader_objects.py
yt_idv/simple_gui.py
yt_idv/traitlets_support.py
yt_idv/yt_idv.py
yt_idv.egg-info/PKG-INFO
yt_idv.egg-info/SOURCES.txt
yt_idv.egg-info/dependency_links.txt
yt_idv.egg-info/entry_points.txt
yt_idv.egg-info/not-zip-safe
yt_idv.egg-info/requires.txt
yt_idv.egg-info/top_level.txt
yt_idv/cameras/__init__.py
yt_idv/cameras/base_camera.py
yt_idv/cameras/trackball_camera.py
yt_idv/rendering_contexts/__init__.py
yt_idv/rendering_contexts/base_context.py
yt_idv/rendering_contexts/base_offscreen.py
yt_idv/rendering_contexts/egl_context.py
yt_idv/rendering_contexts/osmesa_context.py
yt_idv/rendering_contexts/pyglet_context.py
yt_idv/scene_annotations/__init__.py
yt_idv/scene_annotations/base_annotation.py
yt_idv/scene_annotations/block_outline.py
yt_idv/scene_annotations/box.py
yt_idv/scene_annotations/grid_outlines.py
