Metadata-Version: 2.4
Name: yt_idv
Version: 0.5.1
Summary: Interactive Volume Rendering for yt
Home-page: https://github.com/yt-project/yt_idv
Author: Matthew Turk
Author-email: matthewturk@gmail.com
License: BSD-3-Clause
Keywords: yt_idv
Classifier: Development Status :: 2 - Pre-Alpha
Classifier: Intended Audience :: Developers
Classifier: Natural Language :: English
Classifier: Programming Language :: Python :: 3
Classifier: Programming Language :: Python :: 3 :: Only
Classifier: Programming Language :: Python :: 3.9
Classifier: Programming Language :: Python :: 3.10
Classifier: Programming Language :: Python :: 3.11
Classifier: Programming Language :: Python :: 3.12
Classifier: Programming Language :: Python :: Implementation :: CPython
Requires-Python: >=3.9
License-File: LICENSE
Requires-Dist: Click>=7.0
Requires-Dist: cmyt
Requires-Dist: imgui>=1.2.0
Requires-Dist: matplotlib>=3.0
Requires-Dist: numpy>=1.18.0
Requires-Dist: pyOpenGL>=3.1.5
Requires-Dist: pyglet>=2.0.dev0
Requires-Dist: pyyaml>=5.3.1
Requires-Dist: traitlets>=5.0.5
Requires-Dist: traittypes>=0.2.1
Requires-Dist: yt>=4.1.0
Provides-Extra: dev
Requires-Dist: twine==1.14.0; extra == "dev"
Requires-Dist: wheel==0.33.6; extra == "dev"
Provides-Extra: minimal
Requires-Dist: numpy<2.0; extra == "minimal"
Provides-Extra: test
Requires-Dist: pytest>=6.2.4; extra == "test"
Requires-Dist: pytest-html; extra == "test"
Dynamic: license-file
